{
    "name": "App\\Csi",
    "line": 22,
    "short_desc": "Class Csi.",
    "long_desc": "",
    "hint": null,
    "tags": {
        "property": [
            [
                [
                    [
                        "string",
                        false
                    ]
                ],
                "channel_server",
                ""
            ],
            [
                [
                    [
                        "string",
                        false
                    ]
                ],
                "channel",
                ""
            ],
            [
                [
                    [
                        "string",
                        false
                    ]
                ],
                "protocol",
                ""
            ],
            [
                [
                    [
                        "string",
                        false
                    ]
                ],
                "url",
                ""
            ],
            [
                [
                    [
                        "string",
                        false
                    ]
                ],
                "ssm",
                ""
            ],
            [
                [
                    [
                        "string",
                        false
                    ]
                ],
                "imc",
                ""
            ],
            [
                [
                    [
                        "string",
                        false
                    ]
                ],
                "ip",
                ""
            ],
            [
                [
                    [
                        "string",
                        false
                    ]
                ],
                "pid",
                ""
            ]
        ]
    },
    "namespace": "App",
    "file": "\/home\/vagrant\/repos\/manager\/app\/Csi.php",
    "relative_file": null,
    "hash": "75b26e3f25e1c0476ca831b1fd6f055eb6468413",
    "parent": "Illuminate\\Database\\Eloquent\\Model",
    "modifiers": 0,
    "is_trait": false,
    "is_interface": false,
    "aliases": {
        "Model": "Illuminate\\Database\\Eloquent\\Model",
        "SoftDeletes": "Illuminate\\Database\\Eloquent\\SoftDeletes"
    },
    "errors": [],
    "interfaces": [],
    "traits": {
        "Illuminate\\Database\\Eloquent\\SoftDeletes": "Illuminate\\Database\\Eloquent\\SoftDeletes"
    },
    "properties": {
        "fillable": {
            "name": "fillable",
            "line": 26,
            "short_desc": "",
            "long_desc": "",
            "hint": null,
            "hint_desc": null,
            "tags": [],
            "modifiers": 2,
            "default": {
                "nodeType": "Expr_Array",
                "items": [
                    {
                        "nodeType": "Expr_ArrayItem",
                        "key": null,
                        "value": {
                            "nodeType": "Scalar_String",
                            "value": "url",
                            "attributes": {
                                "startLine": 26,
                                "endLine": 26,
                                "kind": 1
                            }
                        },
                        "byRef": false,
                        "attributes": {
                            "startLine": 26,
                            "endLine": 26
                        }
                    },
                    {
                        "nodeType": "Expr_ArrayItem",
                        "key": null,
                        "value": {
                            "nodeType": "Scalar_String",
                            "value": "ssm",
                            "attributes": {
                                "startLine": 26,
                                "endLine": 26,
                                "kind": 1
                            }
                        },
                        "byRef": false,
                        "attributes": {
                            "startLine": 26,
                            "endLine": 26
                        }
                    },
                    {
                        "nodeType": "Expr_ArrayItem",
                        "key": null,
                        "value": {
                            "nodeType": "Scalar_String",
                            "value": "imc",
                            "attributes": {
                                "startLine": 26,
                                "endLine": 26,
                                "kind": 1
                            }
                        },
                        "byRef": false,
                        "attributes": {
                            "startLine": 26,
                            "endLine": 26
                        }
                    },
                    {
                        "nodeType": "Expr_ArrayItem",
                        "key": null,
                        "value": {
                            "nodeType": "Scalar_String",
                            "value": "ip",
                            "attributes": {
                                "startLine": 26,
                                "endLine": 26,
                                "kind": 1
                            }
                        },
                        "byRef": false,
                        "attributes": {
                            "startLine": 26,
                            "endLine": 26
                        }
                    },
                    {
                        "nodeType": "Expr_ArrayItem",
                        "key": null,
                        "value": {
                            "nodeType": "Scalar_String",
                            "value": "pid",
                            "attributes": {
                                "startLine": 26,
                                "endLine": 26,
                                "kind": 1
                            }
                        },
                        "byRef": false,
                        "attributes": {
                            "startLine": 26,
                            "endLine": 26
                        }
                    },
                    {
                        "nodeType": "Expr_ArrayItem",
                        "key": null,
                        "value": {
                            "nodeType": "Scalar_String",
                            "value": "channel_server_id",
                            "attributes": {
                                "startLine": 26,
                                "endLine": 26,
                                "kind": 1
                            }
                        },
                        "byRef": false,
                        "attributes": {
                            "startLine": 26,
                            "endLine": 26
                        }
                    },
                    {
                        "nodeType": "Expr_ArrayItem",
                        "key": null,
                        "value": {
                            "nodeType": "Scalar_String",
                            "value": "channel_id",
                            "attributes": {
                                "startLine": 26,
                                "endLine": 26,
                                "kind": 1
                            }
                        },
                        "byRef": false,
                        "attributes": {
                            "startLine": 26,
                            "endLine": 26
                        }
                    },
                    {
                        "nodeType": "Expr_ArrayItem",
                        "key": null,
                        "value": {
                            "nodeType": "Scalar_String",
                            "value": "protocol_id",
                            "attributes": {
                                "startLine": 26,
                                "endLine": 26,
                                "kind": 1
                            }
                        },
                        "byRef": false,
                        "attributes": {
                            "startLine": 26,
                            "endLine": 26
                        }
                    }
                ],
                "attributes": {
                    "startLine": 26,
                    "endLine": 26,
                    "kind": 2
                }
            },
            "errors": []
        },
        "hidden": {
            "name": "hidden",
            "line": 27,
            "short_desc": "",
            "long_desc": "",
            "hint": null,
            "hint_desc": null,
            "tags": [],
            "modifiers": 2,
            "default": {
                "nodeType": "Expr_Array",
                "items": [],
                "attributes": {
                    "startLine": 27,
                    "endLine": 27,
                    "kind": 2
                }
            },
            "errors": []
        },
        "channel_server": {
            "name": "channel_server",
            "line": 22,
            "short_desc": "",
            "long_desc": null,
            "hint": [
                [
                    "string",
                    false
                ]
            ],
            "hint_desc": null,
            "tags": [],
            "modifiers": null,
            "default": null,
            "errors": []
        },
        "channel": {
            "name": "channel",
            "line": 22,
            "short_desc": "",
            "long_desc": null,
            "hint": [
                [
                    "string",
                    false
                ]
            ],
            "hint_desc": null,
            "tags": [],
            "modifiers": null,
            "default": null,
            "errors": []
        },
        "protocol": {
            "name": "protocol",
            "line": 22,
            "short_desc": "",
            "long_desc": null,
            "hint": [
                [
                    "string",
                    false
                ]
            ],
            "hint_desc": null,
            "tags": [],
            "modifiers": null,
            "default": null,
            "errors": []
        },
        "url": {
            "name": "url",
            "line": 22,
            "short_desc": "",
            "long_desc": null,
            "hint": [
                [
                    "string",
                    false
                ]
            ],
            "hint_desc": null,
            "tags": [],
            "modifiers": null,
            "default": null,
            "errors": []
        },
        "ssm": {
            "name": "ssm",
            "line": 22,
            "short_desc": "",
            "long_desc": null,
            "hint": [
                [
                    "string",
                    false
                ]
            ],
            "hint_desc": null,
            "tags": [],
            "modifiers": null,
            "default": null,
            "errors": []
        },
        "imc": {
            "name": "imc",
            "line": 22,
            "short_desc": "",
            "long_desc": null,
            "hint": [
                [
                    "string",
                    false
                ]
            ],
            "hint_desc": null,
            "tags": [],
            "modifiers": null,
            "default": null,
            "errors": []
        },
        "ip": {
            "name": "ip",
            "line": 22,
            "short_desc": "",
            "long_desc": null,
            "hint": [
                [
                    "string",
                    false
                ]
            ],
            "hint_desc": null,
            "tags": [],
            "modifiers": null,
            "default": null,
            "errors": []
        },
        "pid": {
            "name": "pid",
            "line": 22,
            "short_desc": "",
            "long_desc": null,
            "hint": [
                [
                    "string",
                    false
                ]
            ],
            "hint_desc": null,
            "tags": [],
            "modifiers": null,
            "default": null,
            "errors": []
        }
    },
    "methods": {
        "setChannelServerIdAttribute": {
            "name": "setChannelServerIdAttribute",
            "line": 33,
            "short_desc": "Set to null if empty.",
            "long_desc": "",
            "hint": [
                [
                    "void",
                    false
                ]
            ],
            "hint_desc": null,
            "tags": [],
            "modifiers": 1,
            "is_by_ref": "",
            "exceptions": [],
            "errors": [],
            "parameters": {
                "input": {
                    "name": "input",
                    "line": 33,
                    "short_desc": "",
                    "long_desc": null,
                    "hint": [],
                    "tags": [],
                    "modifiers": null,
                    "default": null,
                    "variadic": false,
                    "is_by_ref": false
                }
            }
        },
        "setChannelIdAttribute": {
            "name": "setChannelIdAttribute",
            "line": 42,
            "short_desc": "Set to null if empty.",
            "long_desc": "",
            "hint": [
                [
                    "void",
                    false
                ]
            ],
            "hint_desc": null,
            "tags": [],
            "modifiers": 1,
            "is_by_ref": "",
            "exceptions": [],
            "errors": [],
            "parameters": {
                "input": {
                    "name": "input",
                    "line": 42,
                    "short_desc": "",
                    "long_desc": null,
                    "hint": [],
                    "tags": [],
                    "modifiers": null,
                    "default": null,
                    "variadic": false,
                    "is_by_ref": false
                }
            }
        },
        "setProtocolIdAttribute": {
            "name": "setProtocolIdAttribute",
            "line": 51,
            "short_desc": "Set to null if empty.",
            "long_desc": "",
            "hint": [
                [
                    "void",
                    false
                ]
            ],
            "hint_desc": null,
            "tags": [],
            "modifiers": 1,
            "is_by_ref": "",
            "exceptions": [],
            "errors": [],
            "parameters": {
                "input": {
                    "name": "input",
                    "line": 51,
                    "short_desc": "",
                    "long_desc": null,
                    "hint": [],
                    "tags": [],
                    "modifiers": null,
                    "default": null,
                    "variadic": false,
                    "is_by_ref": false
                }
            }
        },
        "channel_server": {
            "name": "channel_server",
            "line": 56,
            "short_desc": "",
            "long_desc": "",
            "hint": null,
            "hint_desc": null,
            "tags": [],
            "modifiers": 1,
            "is_by_ref": "",
            "exceptions": [],
            "errors": [],
            "parameters": []
        },
        "channel": {
            "name": "channel",
            "line": 61,
            "short_desc": "",
            "long_desc": "",
            "hint": null,
            "hint_desc": null,
            "tags": [],
            "modifiers": 1,
            "is_by_ref": "",
            "exceptions": [],
            "errors": [],
            "parameters": []
        },
        "protocol": {
            "name": "protocol",
            "line": 66,
            "short_desc": "",
            "long_desc": "",
            "hint": null,
            "hint_desc": null,
            "tags": [],
            "modifiers": 1,
            "is_by_ref": "",
            "exceptions": [],
            "errors": [],
            "parameters": []
        }
    },
    "constants": []
}